cleanup.py
main.py
manage_memory.py
vector_memory.py
mcp_server_vector_memory-0.4.4.dist-info/METADATA
mcp_server_vector_memory-0.4.4.dist-info/WHEEL
mcp_server_vector_memory-0.4.4.dist-info/entry_points.txt
mcp_server_vector_memory-0.4.4.dist-info/licenses/LICENSE
mcp_server_vector_memory-0.4.4.dist-info/RECORD
