Metadata-Version: 2.4
Name: mcp-server-vector-memory
Version: 0.4.4
Summary: MCP server for semantic document memory with Redis vector store
Project-URL: Homepage, https://github.com/NeerajG03/vector-memory
Project-URL: Repository, https://github.com/NeerajG03/vector-memory
Project-URL: Issues, https://github.com/NeerajG03/vector-memory/issues
Author-email: NeerajG03 <neeraj@example.com>
License: MIT
License-File: LICENSE
Keywords: embeddings,mcp,redis,semantic-search,vector-memory
Classifier: Development Status :: 3 - Alpha
Classifier: Intended Audience :: Developers
Classifier: License :: OSI Approved :: MIT License
Classifier: Programming Language :: Python :: 3.12
Requires-Python: >=3.12
Requires-Dist: httpx>=0.28.1
Requires-Dist: langchain-community>=0.3.30
Requires-Dist: langchain-huggingface>=0.3.1
Requires-Dist: langchain-redis>=0.2.4
Requires-Dist: langchain-text-splitters>=0.3.11
Requires-Dist: mcp[cli]>=1.16.0
Requires-Dist: pypdf>=6.1.1
Requires-Dist: scikit-learn>=1.7.2
Requires-Dist: sentence-transformers>=5.1.1
